mcqq_bot/__init__.py
mcqq_bot/cli_start.py
mcqq_bot/ws_server.py
mcqq_bot/cli/__init__.py
mcqq_bot/cli/bot.py
mcqq_bot/cli/utils.py
mcqq_bot/database/__init__.py
mcqq_bot/database/db.py
mcqq_bot/database/models.py
mcqq_bot/plugins/__init__.py
mcqq_bot/plugins/auto_delete.py
mcqq_bot/plugins/connected_servers.py
mcqq_bot/plugins/help.py
mcqq_bot/plugins/servers.py
mcqq_bot/plugins/display_server_name/__init__.py
mcqq_bot/plugins/display_server_name/display_off.py
mcqq_bot/plugins/display_server_name/display_on.py
mcqq_bot/plugins/on_msg/__init__.py
mcqq_bot/plugins/on_msg/data_source.py
mcqq_bot/plugins/rcon/__init__.py
mcqq_bot/plugins/rcon/change_ip.py
mcqq_bot/plugins/rcon/change_password.py
mcqq_bot/plugins/rcon/change_port.py
mcqq_bot/plugins/rcon_cmd/__init__.py
mcqq_bot/plugins/rcon_cmd/rcon_cmd_off.py
mcqq_bot/plugins/rcon_cmd/rcon_cmd_on.py
mcqq_bot/plugins/rcon_msg/__init__.py
mcqq_bot/plugins/rcon_msg/rcon_msg_off.py
mcqq_bot/plugins/rcon_msg/rcon_msg_on.py
mcqq_bot/plugins/send_group_name/__init__.py
mcqq_bot/plugins/send_group_name/send_off.py
mcqq_bot/plugins/send_group_name/send_on.py
mcqq_bot/plugins/sub/__init__.py
mcqq_bot/plugins/sub/add_sub.py
mcqq_bot/plugins/sub/delete_sub.py
mcqq_bot/plugins/sub/sub_list.py
mcqq_bot/utils/__init__.py
mcqq_bot/utils/config.py
mcqq_bot_test-0.1.4.dist-info/LICENSE
mcqq_bot_test-0.1.4.dist-info/METADATA
mcqq_bot_test-0.1.4.dist-info/WHEEL
mcqq_bot_test-0.1.4.dist-info/entry_points.txt
mcqq_bot_test-0.1.4.dist-info/top_level.txt
mcqq_bot_test-0.1.4.dist-info/RECORD
