Metadata-Version: 2.1
Name: mcqq-bot-test
Version: 0.1.4
Summary: 基于NoneBot的QQ群聊与Minecraft Server消息互通插件
Home-page: https://github.com/17TheWord/nonebot-plugin-mcqq
Author: 17TheWord
Author-email: 17theword@gmail.com
Classifier: Programming Language :: Python :: 3.9
Classifier: License :: OSI Approved :: GNU Affero General Public License v3
Classifier: Operating System :: OS Independent
License-File: LICENSE
Requires-Dist: nonebot2 (>=2.0.0rc2)
Requires-Dist: nonebot-adapter-onebot (>=2.1.5)
Requires-Dist: nonebot-plugin-guild-patch (>=0.2.0)
Requires-Dist: nonebot-plugin-gocqhttp (>=0.6.3)
Requires-Dist: websockets (>=10.3)
Requires-Dist: tortoise-orm (>=0.19.2)
Requires-Dist: aio-mc-rcon (>=3.2.0)
Requires-Dist: click (>=8.0.4)
